[
  {
    "Author": "ZeroTheScyther",
    "Name": "Defishinator",
    "InternalName": "Defishinator",
    "AssemblyVersion": "1.0.0.0",
    "Description": "Automatically desynthesises all Seafood-category items from your inventory. Supports bulk desynth for stacks. Use /defish to open the window.",
    "Punchline": "Desynthesises all the fish in your inventory.",
    "RepoUrl": "https://github.com/ZeroTheScyther/Defishinator",
    "ApplicableVersion": "any",
    "DalamudApiLevel": 14,
    "Tags": [ "desynth", "fish", "fishing", "salvage", "automation" ],
    "DownloadLinkInstall": "https://github.com/ZeroTheScyther/Defishinator/releases/latest/download/latest.zip",
    "DownloadLinkUpdate": "https://github.com/ZeroTheScyther/Defishinator/releases/latest/download/latest.zip",
    "DownloadCount": 0
  }
]
